<?xml version="1.0" encoding="utf-8"?>
<manifest
    xmlns:android="http://schemas.android.com/apk/res/android"
    android:versionCode="408"
    android:versionName="4.0.8"
    package="com.Android56">

    <uses-sdk
        android:minSdkVersion="9"
        android:targetSdkVersion="17" />

    <uses-permission
        android:name="android.permission.INTERNET" />

    <uses-permission
        android:name="android.permission.ACCESS_NETWORK_STATE" />

    <uses-permission
        android:name="android.permission.ACCESS_WIFI_STATE" />

    <uses-permission
        android:name="android.permission.CHANGE_CONFIGURATION" />

    <uses-permission
        android:name="android.permission.GET_ACCOUNTS" />

    <uses-permission
        android:name="android.permission.MANAGE_ACCOUNTS" />

    <uses-permission
        android:name="android.permission.READ_PHONE_STATE" />

    <uses-permission
        android:name="android.permission.CAMERA" />

    <uses-permission
        android:name="android.permission.RECORD_AUDIO" />

    <uses-permission
        android:name="android.permission.MODIFY_AUDIO_SETTINGS" />

    <uses-permission
        android:name="android.permission.ACCESS_COARSE_LOCATION" />

    <uses-permission
        android:name="android.permission.WRITE_EXTERNAL_STORAGE" />

    <uses-permission
        android:name="android.permission.RECEIVE_BOOT_COMPLETED" />

    <uses-permission
        android:name="android.permission.VIBRATE" />

    <uses-permission
        android:name="android.permission.BROADCAST_STICKY" />

    <uses-permission
        android:name="android.permission.GET_TASKS" />

    <uses-feature
        android:name="android.hardware.camera" />

    <uses-feature
        android:name="android.hardware.camera.autofocus" />

    <uses-feature
        android:name="android.hardware.camera.any" />

    <uses-feature
        android:name="android.hardware.camera.flash" />

    <uses-permission
        android:name="com.android.launcher.permission.INSTALL_SHORTCUT" />

    <application
        android:theme="@ref/0x01030006"
        android:label="@ref/0x7f090000"
        android:icon="@ref/0x7f020152"
        android:name="com.Android56.common.Application56"
        android:allowBackup="true"
        android:hardwareAccelerated="false">

        <meta-data
            android:name="UMENG_APPKEY"
            android:value="5142ed1556240b7ca6005445" />

        <meta-data
            android:name="UMENG_CHANNEL"
            android:value="应用汇" />

        <meta-data
            android:name="UMENG_CHANNEL_ID"
            android:value="9004001" />

        <activity
            android:name="com.Android56.ActivityLogo"
            android:screenOrientation="1">

            <intent-filter>

                <action
                    android:name="android.intent.action.MAIN" />

                <category
                    android:name="android.intent.category.LAUNCHER" />
            </intent-filter>
        </activity>

        <activity
            android:name="com.Android56.activity.VideoPlayerBaseActivity"
            android:exported="true"
            android:configChanges="0x4a0"
            android:windowSoftInputMode="0x30">

            <intent-filter>

                <action
                    android:name="android.intent.action.VIEW" />

                <category
                    android:name="android.intent.category.LAUNCHER" />
            </intent-filter>
        </activity>

        <activity
            android:name="com.Android56.activity.RecommendSubscribeActivity"
            android:exported="true"
            android:screenOrientation="1"
            android:configChanges="0x4a0"
            android:windowSoftInputMode="0x20" />

        <activity
            android:name="com.Android56.activity.BaseActivity"
            android:launchMode="2"
            android:screenOrientation="1">

            <intent-filter>

                <action
                    android:name="android.intent.action.VIEW" />

                <category
                    android:name="android.intent.category.DEFAULT" />

                <category
                    android:name="android.intent.category.BROWSABLE" />

                <data
                    android:scheme="com.android.56video" />
            </intent-filter>

            <intent-filter>

                <action
                    android:name="android.intent.action.VIEW" />

                <category
                    android:name="android.intent.category.DEFAULT" />

                <data
                    android:mimeType="video/*" />
            </intent-filter>

            <intent-filter>

                <action
                    android:name="android.intent.action.VIEW" />

                <category
                    android:name="android.intent.category.DEFAULT" />

                <category
                    android:name="android.intent.category.BROWSABLE" />

                <data
                    android:scheme="file" />

                <data
                    android:mimeType="*/*" />

                <data
                    android:host="*" />

                <data
                    android:pathPattern=".*\.56com" />
            </intent-filter>

            <intent-filter>

                <action
                    android:name="android.intent.action.VIEW" />

                <category
                    android:name="android.intent.category.DEFAULT" />

                <category
                    android:name="android.intent.category.BROWSABLE" />

                <data
                    android:scheme="content" />

                <data
                    android:host="*" />

                <data
                    android:pathPattern=".*\.56com" />
            </intent-filter>
        </activity>

        <activity
            android:name="com.Android56.activity.ContentSubscribeActivity"
            android:launchMode="1"
            android:screenOrientation="1" />

        <activity
            android:name="com.Android56.activity.SettingsActivity"
            android:screenOrientation="1" />

        <activity
            android:name="com.Android56.activity.FavoritesActivity"
            android:launchMode="1"
            android:screenOrientation="1" />

        <activity
            android:name="com.Android56.activity.AboutActivity"
            android:screenOrientation="1" />

        <activity
            android:name="com.Android56.activity.TopicDetailActivity"
            android:screenOrientation="1"
            android:windowSoftInputMode="0x10"
            android:hardwareAccelerated="true" />

        <activity
            android:name="com.Android56.activity.UmengActivity"
            android:screenOrientation="1" />

        <activity
            android:name="com.tencent.tauth.AuthActivity"
            android:launchMode="2"
            android:noHistory="true">

            <intent-filter>

                <action
                    android:name="android.intent.action.VIEW" />

                <category
                    android:name="android.intent.category.DEFAULT" />

                <category
                    android:name="android.intent.category.BROWSABLE" />

                <data
                    android:scheme="tencent204566" />
            </intent-filter>
        </activity>

        <activity
            android:theme="@ref/0x01030010"
            android:name="com.tencent.connect.common.AssistActivity"
            android:screenOrientation="1" />

        <activity
            android:name="com.renn.rennsdk.oauth.OAuthActivity"
            android:launchMode="2" />

        <activity
            android:label="@ref/0x7f090000"
            android:name="com.Android56.activity.RegisterActivity"
            android:launchMode="1"
            android:screenOrientation="1" />

        <activity
            android:label="@ref/0x7f090000"
            android:name="com.Android56.activity.LoginActivity"
            android:launchMode="2"
            android:screenOrientation="1"
            android:windowSoftInputMode="0x10" />

        <activity
            android:name="com.Android56.activity.Activity56UserAgreement"
            android:launchMode="3"
            android:configChanges="0x4a0" />

        <activity
            android:name="com.Android56.activity.CameraActivity"
            android:screenOrientation="1" />

        <activity
            android:name="com.Android56.activity.VideoInfoEditActivity"
            android:launchMode="2"
            android:screenOrientation="1"
            android:windowSoftInputMode="0x34" />

        <activity
            android:name="com.Android56.activity.WebViewActivity"
            android:configChanges="0x4a0"
            android:hardwareAccelerated="true" />

        <activity
            android:name=".activity.UploadManageActivity"
            android:launchMode="1"
            android:screenOrientation="1" />

        <activity
            android:name="com.Android56.activity.SearchActivity"
            android:screenOrientation="1"
            android:windowSoftInputMode="0x10" />

        <activity
            android:name="com.Android56.activity.PlayRecordActivity"
            android:screenOrientation="1" />

        <activity
            android:theme="@ref/0x0103000f"
            android:name=".wxapi.WXEntryActivity"
            android:exported="true" />

        <activity
            android:name="com.Android56.activity.MyVideoActivity"
            android:launchMode="1"
            android:screenOrientation="1" />

        <activity
            android:name="com.Android56.activity.JoinTopicActivity"
            android:screenOrientation="1"
            android:windowSoftInputMode="0x10" />

        <activity
            android:name="com.Android56.activity.FeedbackActivity"
            android:launchMode="3"
            android:screenOrientation="1" />

        <activity
            android:theme="@ref/0x0103000b"
            android:name="com.Android56.activity.ActivityNoSpaceDialog"
            android:screenOrientation="1" />

        <activity
            android:theme="@ref/0x7f0b0006"
            android:name="com.Android56.activity.ShareActivity"
            android:windowSoftInputMode="0x10" />

        <activity
            android:name="com.Android56.activity.TopicCommentsActivity"
            android:screenOrientation="1"
            android:windowSoftInputMode="0x12" />

        <activity
            android:theme="@ref/0x0103000f"
            android:name="com.Android56.activity.VideoDetailCommentActivity"
            android:screenOrientation="1"
            android:windowSoftInputMode="0x15" />

        <activity
            android:name="com.Android56.activity.CloseStoryActivity"
            android:screenOrientation="1" />

        <service
            android:name=".service.UploadService" />

        <service
            android:name="com.Android56.service.DownloadService" />

        <provider
            android:name="com.Android56.data.UploadContentProvider"
            android:authorities="com.Android56.upload" />

        <provider
            android:name="com.Android56.data.OfflineProvider"
            android:authorities="com.Android56.offline" />

        <service
            android:name="com.Android56.service.ServiceOffline" />

        <service
            android:name="com.umeng.common.net.DownloadingService"
            android:exported="true"
            android:process=":DownloadingService" />

        <receiver
            android:name=".receiver.MyBroadCastReceiver">

            <intent-filter>

                <action
                    android:name="android.net.wifi.STATE_CHANGE" />

                <action
                    android:name="android.net.conn.CONNECTIVITY_CHANGE" />

                <action
                    android:name="android.net.conn.edit_downloading" />

                <action
                    android:name="android.net.conn.edit_downloading_commit" />
            </intent-filter>
        </receiver>

        <service
            android:name="com.Android56.service.UpdateService" />

        <receiver
            android:name=".receiver.StartupEventReceiver">

            <intent-filter>

                <action
                    android:name="android.intent.action.BOOT_COMPLETED" />

                <category
                    android:name="android.intent.category.LAUNCHER" />
            </intent-filter>
        </receiver>

        <service
            android:name=".service.PushIntentService" />
    </application>
</manifest>
