<?xml version="1.0" encoding="utf-8"?>
<manifest
    xmlns:android="http://schemas.android.com/apk/res/android"
    android:versionCode="1"
    android:versionName="1.0.0"
    package="com.War.air.raid.fungame">

    <uses-sdk
        android:minSdkVersion="4" />

    <application
        android:label="@ref/0x7f030000"
        android:icon="@ref/0x7f020001">

        <activity
            android:theme="@ref/0x01030007"
            android:name="hll.kxyfyh.act.GameMain"
            android:screenOrientation="0"
            android:configChanges="0xa0">

            <intent-filter>

                <action
                    android:name="com.joy.start.main.screen" />

                <category
                    android:name="android.intent.category.DEFAULT" />
            </intent-filter>
        </activity>

        <activity
            android:name="com.letang.adunion.ads.JoyAdJoymeng"
            android:launchMode="3"
            android:screenOrientation="1" />

        <activity
            android:name="com.google.ads.AdActivity"
            android:screenOrientation="0"
            android:configChanges="0xfb0" />

        <activity
            android:theme="@ref/0x01030010"
            android:name="com.millennialmedia.android.MMActivity"
            android:configChanges="0xb0" />

        <activity
            android:name="com.millennialmedia.android.VideoPlayer"
            android:configChanges="0xb0" />

        <activity
            android:theme="@ref/0x0103000b"
            android:name="com.playhaven.src.publishersdk.content.PHContentView"
            android:windowSoftInputMode="0x10" />

        <activity
            android:theme="@ref/0x01030010"
            android:name="com.chartboost.sdk.CBImpressionActivity"
            android:excludeFromRecents="true" />

        <activity
            android:name="com.flurry.android.FlurryFullscreenTakeoverActivity"
            android:configChanges="0x3b0" />

        <activity
            android:name="com.greystripe.sdk.GSFullscreenActivity"
            android:configChanges="0x4b0" />

        <activity
            android:name="com.joymeng.sprinkle.ui.SprinkleRealAppwallActivity" />

        <activity
            android:theme="@ref/0x0103000f"
            android:name="com.joymeng.sprinkle.ui.SprinkleWebActivity"
            android:launchMode="1"
            android:configChanges="0xb0"
            android:windowSoftInputMode="0x10" />

        <service
            android:name="com.joymeng.sprinkle.service.SprinkleControlerService">

            <intent-filter>

                <action
                    android:name="com.sprinkle.service.joyalive.com.War.air.raid.fungame.notify.game" />

                <action
                    android:name="com.sprinkle.service.joyalive.com.War.air.raid.fungame.check.fullscreen.ad.update.show" />

                <action
                    android:name="com.sprinkle.service.joyalive.com.War.air.raid.fungame.check.fullscreen.ad.update" />

                <action
                    android:name="com.sprinkle.service.joyalive.com.War.air.raid.fungame.show.fullscreen.ad" />

                <action
                    android:name="com.sprinkle.service.joyalive.com.War.air.raid.fungame.install.finish.pack" />

                <action
                    android:name="com.sprinkle.service.joyalive.com.War.air.raid.fungame.download.file" />

                <action
                    android:name="com.sprinkle.service.joyalive.com.War.air.raid.fungame.record.failed.file" />

                <action
                    android:name="com.sprinkle.service.joyalive.com.War.air.raid.fungame.resume.failed.downloads" />

                <action
                    android:name="com.sprinkle.service.joyalive.com.War.air.raid.fungame.show.slider.view" />

                <action
                    android:name="com.sprinkle.service.joyalive.com.War.air.raid.fungame.check.update.show.slider.view" />

                <action
                    android:name="com.sprinkle.service.joyalive.com.War.air.raid.fungame.usr.remove.pacakge" />
            </intent-filter>
        </service>

        <receiver
            android:name="com.joymeng.sprinkle.service.SprinkleControllerReceiver">

            <action
                android:name="android.intent.action.PACKAGE_REMOVED" />

            <action
                android:name="android.intent.action.ACTION_PACKAGE_ADDED" />

            <data
                android:scheme="package" />
        </receiver>

        <activity
            android:theme="@ref/0x01030010"
            android:name="com.mobclix.android.sdk.MobclixBrowserActivity"
            android:hardwareAccelerated="true" />

        <activity
            android:name="com.inmobi.androidsdk.IMBrowserActivity"
            android:configChanges="0xcb0" />

        <activity
            android:theme="@ref/0x01030011"
            android:name="com.jirbo.adcolony.AdColonyOverlay"
            android:configChanges="0xa0" />

        <activity
            android:theme="@ref/0x0103000a"
            android:name="com.jirbo.adcolony.AdColonyFullscreen"
            android:configChanges="0xa0" />

        <activity
            android:theme="@ref/0x0103000a"
            android:name="com.jirbo.adcolony.AdColonyBrowser"
            android:configChanges="0xa0" />

        <activity
            android:name="com.tapjoy.TapjoyFullScreenAdWebView"
            android:configChanges="0xa0" />

        <activity
            android:theme="@ref/0x01030010"
            android:label="@ref/0x7f030000"
            android:name="com.example.client.MainActivity">

            <intent-filter>

                <action
                    android:name="android.intent.action.MAIN" />

                <category
                    android:name="android.intent.category.LAUNCHER" />
            </intent-filter>
        </activity>
    </application>

    <uses-permission
        android:name="android.permission.READ_PHONE_STATE" />

    <uses-permission
        android:name="android.permission.WAKE_LOCK" />

    <uses-permission
        android:name="android.permission.INTERNET" />

    <uses-permission
        android:name="android.permission.GET_TASKS" />

    <uses-permission
        android:name="android.permission.WRITE_EXTERNAL_STORAGE" />

    <uses-permission
        android:name="android.permission.ACCESS_NETWORK_STATE" />

    <uses-permission
        android:name="android.permission.ACCESS_WIFI_STATE" />

    <uses-permission
        android:name="android.permission.VIBRATE" />

    <uses-permission
        android:name="android.permission.GET_ACCOUNTS" />
</manifest>
